{
"type": "FeatureCollection",
"name": "Нижнеудинск_объекты",
"crs": { "type": "name", "properties": { "name": "urn:ogc:def:crs:OGC:1.3:CRS84" } },
"features": [
{ "type": "Feature", "properties": { "fid": 1, "Type": "parking" }, "geometry": { "type": "Point", "coordinates": [ 99.041017947578496, 54.908809708352173 ] } },
{ "type": "Feature", "properties": { "fid": 2, "Type": "calm" }, "geometry": { "type": "Point", "coordinates": [ 99.043416143010106, 54.910089096811227 ] } },
{ "type": "Feature", "properties": { "fid": 3, "Type": "active" }, "geometry": { "type": "Point", "coordinates": [ 99.043780668715726, 54.909945719093287 ] } },
{ "type": "Feature", "properties": { "fid": 4, "Type": "active" }, "geometry": { "type": "Point", "coordinates": [ 99.043780668715726, 54.909669991277227 ] } },
{ "type": "Feature", "properties": { "fid": 5, "Type": "calm" }, "geometry": { "type": "Point", "coordinates": [ 99.044845467487349, 54.90984094274566 ] } },
{ "type": "Feature", "properties": { "fid": 6, "Type": "picnic" }, "geometry": { "type": "Point", "coordinates": [ 99.045449812736123, 54.909532126660942 ] } },
{ "type": "Feature", "properties": { "fid": 7, "Type": "parking" }, "geometry": { "type": "Point", "coordinates": [ 99.046092529111803, 54.908699414339836 ] } },
{ "type": "Feature", "properties": { "fid": 8, "Type": "parking" }, "geometry": { "type": "Point", "coordinates": [ 99.043444921355274, 54.907954921852294 ] } },
{ "type": "Feature", "properties": { "fid": 9, "Type": "calm" }, "geometry": { "type": "Point", "coordinates": [ 99.044912616959451, 54.908815223044861 ] } },
{ "type": "Feature", "properties": { "fid": 10, "Type": "calm" }, "geometry": { "type": "Point", "coordinates": [ 99.044941395304605, 54.908528458023504 ] } },
{ "type": "Feature", "properties": { "fid": 11, "Type": "cinema" }, "geometry": { "type": "Point", "coordinates": [ 99.044202751111669, 54.908550516943819 ] } },
{ "type": "Feature", "properties": { "fid": 12, "Type": "calm" }, "geometry": { "type": "Point", "coordinates": [ 99.043617591426369, 54.908633237787377 ] } },
{ "type": "Feature", "properties": { "fid": 13, "Type": "calm" }, "geometry": { "type": "Point", "coordinates": [ 99.042936503923784, 54.908743531981038 ] } },
{ "type": "Feature", "properties": { "fid": 14, "Type": "art" }, "geometry": { "type": "Point", "coordinates": [ 99.042955689487229, 54.908478825408572 ] } },
{ "type": "Feature", "properties": { "fid": 15, "Type": "calm" }, "geometry": { "type": "Point", "coordinates": [ 99.0433777718832, 54.909135073927928 ] } },
{ "type": "Feature", "properties": { "fid": 16, "Type": "tradepost" }, "geometry": { "type": "Point", "coordinates": [ 99.042524014309564, 54.909157132515837 ] } },
{ "type": "Feature", "properties": { "fid": 17, "Type": "toilet" }, "geometry": { "type": "Point", "coordinates": [ 99.042370529801914, 54.909096471369999 ] } },
{ "type": "Feature", "properties": { "fid": 18, "Type": "playground" }, "geometry": { "type": "Point", "coordinates": [ 99.041555143355168, 54.909008236812859 ] } }
]
}
